// class version 50.0 (50)
// access flags 0x421
public abstract class bdd extends bcd  {

  // compiled from: GuiContainer.java

  @Lcpw/mods/fml/relauncher/SideOnly;(value=Lcpw/mods/fml/relauncher/Side;.CLIENT)

  // access flags 0x1C
  protected final static Lbqo; a

  // access flags 0x4
  protected I f

  // access flags 0x4
  protected I g

  // access flags 0x1
  public Lye; h

  // access flags 0x4
  protected I i

  // access flags 0x4
  protected I r

  // access flags 0x2
  private Lzk; u

  // access flags 0x2
  private Lzk; v

  // access flags 0x2
  private Z w

  // access flags 0x2
  private Labp; x

  // access flags 0x2
  private I y

  // access flags 0x2
  private I z

  // access flags 0x2
  private Lzk; A

  // access flags 0x2
  private J B

  // access flags 0x2
  private Labp; C

  // access flags 0x2
  private Lzk; D

  // access flags 0x2
  private J E

  // access flags 0x14
  protected final Ljava/util/Set; s

  // access flags 0x4
  protected Z t

  // access flags 0x2
  private I F

  // access flags 0x2
  private I G

  // access flags 0x2
  private Z H

  // access flags 0x2
  private I I

  // access flags 0x2
  private J J

  // access flags 0x2
  private Lzk; K

  // access flags 0x2
  private I L

  // access flags 0x2
  private Z M

  // access flags 0x2
  private Labp; N

  // access flags 0x1A
  private final static Ljava/lang/String; __OBFID = "CL_00000737"

  // access flags 0x1
  public Lcodechicken/nei/guihook/GuiContainerManager; manager

  // access flags 0x1
  public <init>(Lye;)V
   L0
    LINENUMBER 60 L0
    ALOAD 0
    INVOKESPECIAL bcd.<init> ()V
   L1
    LINENUMBER 30 L1
    ALOAD 0
    SIPUSH 176
    PUTFIELD bdd.f : I
   L2
    LINENUMBER 31 L2
    ALOAD 0
    SIPUSH 166
    PUTFIELD bdd.g : I
   L3
    LINENUMBER 46 L3
    ALOAD 0
    NEW java/util/HashSet
    DUP
    INVOKESPECIAL java/util/HashSet.<init> ()V
    PUTFIELD bdd.s : Ljava/util/Set;
   L4
    LINENUMBER 61 L4
    ALOAD 0
    ALOAD 1
    PUTFIELD bdd.h : Lye;
   L5
    LINENUMBER 62 L5
    ALOAD 0
    ICONST_1
    PUTFIELD bdd.H : Z
   L6
    LINENUMBER 63 L6
    RETURN
   L7
    LOCALVARIABLE this Lbdd; L0 L7 0
    LOCALVARIABLE par1Container Lye; L0 L7 1
    MAXSTACK = 3
    MAXLOCALS = 2

  // access flags 0x1
  public r_()V
   L0
    LINENUMBER 67 L0
    ALOAD 0
    INVOKESPECIAL bcd.r_ ()V
   L1
    LINENUMBER 68 L1
    ALOAD 0
    GETFIELD bdd.k : Lazd;
    GETFIELD azd.h : Lbje;
    ALOAD 0
    GETFIELD bdd.h : Lye;
    PUTFIELD bje.bp : Lye;
   L2
    LINENUMBER 69 L2
    ALOAD 0
    ALOAD 0
    GETFIELD bdd.l : I
    ALOAD 0
    GETFIELD bdd.f : I
    ISUB
    ICONST_2
    IDIV
    PUTFIELD bdd.i : I
   L3
    LINENUMBER 70 L3
    ALOAD 0
    ALOAD 0
    GETFIELD bdd.m : I
    ALOAD 0
    GETFIELD bdd.g : I
    ISUB
    ICONST_2
    IDIV
    PUTFIELD bdd.r : I
   L4
    LINENUMBER 71 L4
    RETURN
   L5
    LOCALVARIABLE this Lbdd; L0 L5 0
    MAXSTACK = 3
    MAXLOCALS = 1

  // access flags 0x1
  public a(IIF)V
   L0
    LINENUMBER 174 L0
    ALOAD 0
    GETFIELD bdd.manager : Lcodechicken/nei/guihook/GuiContainerManager;
    INVOKEVIRTUAL codechicken/nei/guihook/GuiContainerManager.preDraw ()V
   L1
    LINENUMBER 75 L1
    ALOAD 0
    INVOKEVIRTUAL bdd.q_ ()V
   L2
    LINENUMBER 76 L2
    ALOAD 0
    GETFIELD bdd.i : I
    ISTORE 4
   L3
    LINENUMBER 77 L3
    ALOAD 0
    GETFIELD bdd.r : I
    ISTORE 5
   L4
    LINENUMBER 78 L4
    ALOAD 0
    FLOAD 3
    ILOAD 1
    ILOAD 2
    INVOKEVIRTUAL bdd.a (FII)V
   L5
    LINENUMBER 79 L5
    LDC 32826
    INVOKESTATIC org/lwjgl/opengl/GL11.glDisable (I)V
   L6
    LINENUMBER 80 L6
    INVOKESTATIC azb.a ()V
   L7
    LINENUMBER 81 L7
    SIPUSH 2896
    INVOKESTATIC org/lwjgl/opengl/GL11.glDisable (I)V
   L8
    LINENUMBER 82 L8
    SIPUSH 2929
    INVOKESTATIC org/lwjgl/opengl/GL11.glDisable (I)V
   L9
    LINENUMBER 83 L9
    ALOAD 0
    ILOAD 1
    ILOAD 2
    FLOAD 3
    INVOKESPECIAL bcd.a (IIF)V
   L10
    LINENUMBER 84 L10
    INVOKESTATIC azb.c ()V
   L11
    LINENUMBER 85 L11
    INVOKESTATIC org/lwjgl/opengl/GL11.glPushMatrix ()V
   L12
    LINENUMBER 86 L12
    ILOAD 4
    I2F
    ILOAD 5
    I2F
    FCONST_0
    INVOKESTATIC org/lwjgl/opengl/GL11.glTranslatef (FFF)V
   L13
    LINENUMBER 87 L13
    FCONST_1
    FCONST_1
    FCONST_1
    FCONST_1
    INVOKESTATIC org/lwjgl/opengl/GL11.glColor4f (FFFF)V
   L14
    LINENUMBER 88 L14
    LDC 32826
    INVOKESTATIC org/lwjgl/opengl/GL11.glEnable (I)V
   L15
    LINENUMBER 89 L15
    ALOAD 0
    ACONST_NULL
    PUTFIELD bdd.u : Lzk;
   L16
    LINENUMBER 90 L16
    SIPUSH 240
    ISTORE 6
   L17
    LINENUMBER 91 L17
    SIPUSH 240
    ISTORE 7
   L18
    LINENUMBER 92 L18
    GETSTATIC bul.c : I
    ILOAD 6
    I2F
    FCONST_1
    FDIV
    ILOAD 7
    I2F
    FCONST_1
    FDIV
    INVOKESTATIC bul.a (IFF)V
   L19
    LINENUMBER 93 L19
    FCONST_1
    FCONST_1
    FCONST_1
    FCONST_1
    INVOKESTATIC org/lwjgl/opengl/GL11.glColor4f (FFFF)V
   L20
    LINENUMBER 96 L20
    ICONST_0
    ISTORE 8
   L21
   FRAME FULL [bdd I I F I I I I I] []
    ILOAD 8
    ALOAD 0
    GETFIELD bdd.h : Lye;
    GETFIELD ye.c : Ljava/util/List;
    INVOKEINTERFACE java/util/List.size ()I
    IF_ICMPGE L22
   L23
    LINENUMBER 98 L23
    ALOAD 0
    GETFIELD bdd.h : Lye;
    GETFIELD ye.c : Ljava/util/List;
    ILOAD 8
    INVOKEINTERFACE java/util/List.get (I)Ljava/lang/Object;
    CHECKCAST zk
    ASTORE 9
   L24
    LINENUMBER 99 L24
    ALOAD 0
    ALOAD 9
    INVOKESPECIAL bdd.a (Lzk;)V
   L25
    LINENUMBER 101 L25
    ALOAD 0
    ALOAD 9
    ILOAD 1
    ILOAD 2
    INVOKESPECIAL bdd.a (Lzk;II)Z
    IFEQ L26
    ALOAD 9
    INVOKEVIRTUAL zk.b ()Z
    IFEQ L26
    ALOAD 0
    GETFIELD bdd.manager : Lcodechicken/nei/guihook/GuiContainerManager;
    ILOAD 1
    ILOAD 2
    INVOKEVIRTUAL codechicken/nei/guihook/GuiContainerManager.objectUnderMouse (II)Z
    IFNE L26
   L27
    LINENUMBER 103 L27
    ALOAD 0
    ALOAD 9
    PUTFIELD bdd.u : Lzk;
   L28
    LINENUMBER 104 L28
    SIPUSH 2896
    INVOKESTATIC org/lwjgl/opengl/GL11.glDisable (I)V
   L29
    LINENUMBER 105 L29
    SIPUSH 2929
    INVOKESTATIC org/lwjgl/opengl/GL11.glDisable (I)V
   L30
    LINENUMBER 106 L30
    ALOAD 9
    GETFIELD zk.h : I
    ISTORE 10
   L31
    LINENUMBER 107 L31
    ALOAD 9
    GETFIELD zk.i : I
    ISTORE 11
   L32
    LINENUMBER 108 L32
    ICONST_1
    ICONST_1
    ICONST_1
    ICONST_0
    INVOKESTATIC org/lwjgl/opengl/GL11.glColorMask (ZZZZ)V
   L33
    LINENUMBER 109 L33
    ALOAD 0
    ILOAD 10
    ILOAD 11
    ILOAD 10
    BIPUSH 16
    IADD
    ILOAD 11
    BIPUSH 16
    IADD
    LDC -2130706433
    LDC -2130706433
    INVOKEVIRTUAL bdd.a (IIIIII)V
   L34
    LINENUMBER 110 L34
    ICONST_1
    ICONST_1
    ICONST_1
    ICONST_1
    INVOKESTATIC org/lwjgl/opengl/GL11.glColorMask (ZZZZ)V
   L35
    LINENUMBER 111 L35
    SIPUSH 2896
    INVOKESTATIC org/lwjgl/opengl/GL11.glEnable (I)V
   L36
    LINENUMBER 112 L36
    SIPUSH 2929
    INVOKESTATIC org/lwjgl/opengl/GL11.glEnable (I)V
   L26
    LINENUMBER 96 L26
   FRAME FULL [bdd I I F I I I I I zk] []
    IINC 8 1
    GOTO L21
   L22
    LINENUMBER 118 L22
   FRAME FULL [bdd I I F I I I I I] []
    SIPUSH 2896
    INVOKESTATIC org/lwjgl/opengl/GL11.glDisable (I)V
   L37
    LINENUMBER 119 L37
    ALOAD 0
    ILOAD 1
    ILOAD 2
    INVOKEVIRTUAL bdd.b (II)V
   L38
    LINENUMBER 120 L38
    SIPUSH 2896
    INVOKESTATIC org/lwjgl/opengl/GL11.glEnable (I)V
    ALOAD 0
    GETFIELD bdd.manager : Lcodechicken/nei/guihook/GuiContainerManager;
    ILOAD 1
    ILOAD 2
    INVOKEVIRTUAL codechicken/nei/guihook/GuiContainerManager.renderObjects (II)V
   L39
    LINENUMBER 121 L39
    ALOAD 0
    GETFIELD bdd.k : Lazd;
    GETFIELD azd.h : Lbje;
    GETFIELD bje.bn : Lxj;
    ASTORE 8
   L40
    LINENUMBER 122 L40
    ALOAD 0
    GETFIELD bdd.x : Labp;
    IFNONNULL L41
    ALOAD 8
    INVOKEVIRTUAL xj.o ()Labp;
    GOTO L42
   L41
   FRAME FULL [bdd I I F I I I I xj] []
    ALOAD 0
    GETFIELD bdd.x : Labp;
   L42
   FRAME FULL [bdd I I F I I I I xj] [abp]
    ASTORE 9
   L43
    LINENUMBER 124 L43
    ALOAD 9
    IFNULL L44
   L45
    LINENUMBER 126 L45
    BIPUSH 8
    ISTORE 10
   L46
    LINENUMBER 127 L46
    ALOAD 0
    GETFIELD bdd.x : Labp;
    IFNONNULL L47
    BIPUSH 8
    GOTO L48
   L47
   FRAME FULL [bdd I I F I I I I xj abp I] []
    BIPUSH 16
   L48
   FRAME FULL [bdd I I F I I I I xj abp I] [I]
    ISTORE 11
   L49
    LINENUMBER 128 L49
    ACONST_NULL
    ASTORE 12
   L50
    LINENUMBER 130 L50
    ALOAD 0
    GETFIELD bdd.x : Labp;
    IFNULL L51
    ALOAD 0
    GETFIELD bdd.w : Z
    IFEQ L51
   L52
    LINENUMBER 132 L52
    ALOAD 9
    INVOKEVIRTUAL abp.m ()Labp;
    ASTORE 9
   L53
    LINENUMBER 133 L53
    ALOAD 9
    ALOAD 9
    GETFIELD abp.b : I
    I2F
    FCONST_2
    FDIV
    INVOKESTATIC ou.f (F)I
    PUTFIELD abp.b : I
    GOTO L54
   L51
    LINENUMBER 135 L51
   FRAME FULL [bdd I I F I I I I xj abp I I N] []
    ALOAD 0
    GETFIELD bdd.t : Z
    IFEQ L54
    ALOAD 0
    GETFIELD bdd.s : Ljava/util/Set;
    INVOKEINTERFACE java/util/Set.size ()I
    ICONST_1
    IF_ICMPLE L54
   L55
    LINENUMBER 137 L55
    ALOAD 9
    INVOKEVIRTUAL abp.m ()Labp;
    ASTORE 9
   L56
    LINENUMBER 138 L56
    ALOAD 9
    ALOAD 0
    GETFIELD bdd.I : I
    PUTFIELD abp.b : I
   L57
    LINENUMBER 140 L57
    ALOAD 9
    GETFIELD abp.b : I
    IFNE L54
   L58
    LINENUMBER 142 L58
    NEW java/lang/StringBuilder
    DUP
    INVOKESPECIAL java/lang/StringBuilder.<init> ()V
    LDC ""
    INVOKEVIRTUAL java/lang/StringBuilder.append (Ljava/lang/String;)Ljava/lang/StringBuilder;
    GETSTATIC a.o : La;
    INVOKEVIRTUAL java/lang/StringBuilder.append (Ljava/lang/Object;)Ljava/lang/StringBuilder;
    LDC "0"
    INVOKEVIRTUAL java/lang/StringBuilder.append (Ljava/lang/String;)Ljava/lang/StringBuilder;
    INVOKEVIRTUAL java/lang/StringBuilder.toString ()Ljava/lang/String;
    ASTORE 12
   L54
    LINENUMBER 146 L54
   FRAME FULL [bdd I I F I I I I xj abp I I java/lang/String] []
    ALOAD 0
    ALOAD 9
    ILOAD 1
    ILOAD 4
    ISUB
    ILOAD 10
    ISUB
    ILOAD 2
    ILOAD 5
    ISUB
    ILOAD 11
    ISUB
    ALOAD 12
    INVOKESPECIAL bdd.a (Labp;IILjava/lang/String;)V
   L44
    LINENUMBER 149 L44
   FRAME FULL [bdd I I F I I I I xj abp] []
    ALOAD 0
    GETFIELD bdd.C : Labp;
    IFNULL L59
   L60
    LINENUMBER 151 L60
    INVOKESTATIC azd.J ()J
    ALOAD 0
    GETFIELD bdd.B : J
    LSUB
    L2F
    LDC 100.0
    FDIV
    FSTORE 10
   L61
    LINENUMBER 153 L61
    FLOAD 10
    FCONST_1
    FCMPL
    IFLT L62
   L63
    LINENUMBER 155 L63
    FCONST_1
    FSTORE 10
   L64
    LINENUMBER 156 L64
    ALOAD 0
    ACONST_NULL
    PUTFIELD bdd.C : Labp;
   L62
    LINENUMBER 159 L62
   FRAME FULL [bdd I I F I I I I xj abp F] []
    ALOAD 0
    GETFIELD bdd.A : Lzk;
    GETFIELD zk.h : I
    ALOAD 0
    GETFIELD bdd.y : I
    ISUB
    ISTORE 11
   L65
    LINENUMBER 160 L65
    ALOAD 0
    GETFIELD bdd.A : Lzk;
    GETFIELD zk.i : I
    ALOAD 0
    GETFIELD bdd.z : I
    ISUB
    ISTORE 12
   L66
    LINENUMBER 161 L66
    ALOAD 0
    GETFIELD bdd.y : I
    ILOAD 11
    I2F
    FLOAD 10
    FMUL
    F2I
    IADD
    ISTORE 13
   L67
    LINENUMBER 162 L67
    ALOAD 0
    GETFIELD bdd.z : I
    ILOAD 12
    I2F
    FLOAD 10
    FMUL
    F2I
    IADD
    ISTORE 14
   L68
    LINENUMBER 163 L68
    ALOAD 0
    ALOAD 0
    GETFIELD bdd.C : Labp;
    ILOAD 13
    ILOAD 14
    ACONST_NULL
    CHECKCAST java/lang/String
    INVOKESPECIAL bdd.a (Labp;IILjava/lang/String;)V
   L59
    LINENUMBER 166 L59
   FRAME FULL [bdd I I F I I I I xj abp] []
    INVOKESTATIC org/lwjgl/opengl/GL11.glPopMatrix ()V
    ALOAD 0
    GETFIELD bdd.manager : Lcodechicken/nei/guihook/GuiContainerManager;
    ILOAD 1
    ILOAD 2
    INVOKEVIRTUAL codechicken/nei/guihook/GuiContainerManager.renderToolTips (II)V
    SIPUSH 2896
    INVOKESTATIC org/lwjgl/opengl/GL11.glEnable (I)V
   L69
    LINENUMBER 175 L69
    SIPUSH 2929
    INVOKESTATIC org/lwjgl/opengl/GL11.glEnable (I)V
   L70
    LINENUMBER 176 L70
    INVOKESTATIC azb.b ()V
   L71
    LINENUMBER 177 L71
    RETURN
   L72
    LOCALVARIABLE j1 I L31 L26 10
    LOCALVARIABLE k1 I L32 L26 11
    LOCALVARIABLE slot Lzk; L24 L26 9
    LOCALVARIABLE i1 I L21 L22 8
    LOCALVARIABLE b0 B L46 L44 10
    LOCALVARIABLE s Ljava/lang/String; L50 L44 12
    LOCALVARIABLE k1 I L49 L44 11
    LOCALVARIABLE f1 F L61 L59 10
    LOCALVARIABLE j2 I L66 L59 12
    LOCALVARIABLE l1 I L67 L59 13
    LOCALVARIABLE i2 I L68 L59 14
    LOCALVARIABLE k1 I L65 L59 11
    LOCALVARIABLE itemstack1 Labp; L0 L0 10
    LOCALVARIABLE this Lbdd; L1 L72 0
    LOCALVARIABLE par1 I L1 L72 1
    LOCALVARIABLE par2 I L1 L72 2
    LOCALVARIABLE par3 F L1 L72 3
    LOCALVARIABLE k I L3 L72 4
    LOCALVARIABLE l I L4 L72 5
    LOCALVARIABLE short1 S L17 L72 6
    LOCALVARIABLE short2 S L18 L72 7
    LOCALVARIABLE inventoryplayer Lxj; L40 L72 8
    LOCALVARIABLE itemstack Labp; L43 L72 9
    MAXSTACK = 7
    MAXLOCALS = 15

  // access flags 0x2
  private a(Labp;IILjava/lang/String;)V
   L0
    LINENUMBER 181 L0
    FCONST_0
    FCONST_0
    LDC 32.0
    INVOKESTATIC org/lwjgl/opengl/GL11.glTranslatef (FFF)V
   L1
    LINENUMBER 182 L1
    ALOAD 0
    LDC 500.0
    PUTFIELD bdd.e : F
   L2
    LINENUMBER 183 L2
    GETSTATIC bdd.j : Lbnq;
    LDC 500.0
    PUTFIELD bnq.f : F
   L3
    LINENUMBER 184 L3
    ACONST_NULL
    ASTORE 5
   L4
    LINENUMBER 185 L4
    ALOAD 1
    IFNULL L5
    ALOAD 1
    INVOKEVIRTUAL abp.b ()Labn;
    ALOAD 1
    INVOKEVIRTUAL abn.getFontRenderer (Labp;)Lbag;
    ASTORE 5
   L5
    LINENUMBER 186 L5
   FRAME FULL [bdd abp I I java/lang/String bag] []
    ALOAD 5
    IFNONNULL L6
    ALOAD 0
    GETFIELD bdd.q : Lbag;
    ASTORE 5
   L6
    LINENUMBER 187 L6
   FRAME FULL [bdd abp I I java/lang/String bag] []
    GETSTATIC bdd.j : Lbnq;
    ALOAD 5
    ALOAD 0
    GETFIELD bdd.k : Lazd;
    INVOKEVIRTUAL azd.N ()Lbpx;
    ALOAD 1
    ILOAD 2
    ILOAD 3
    INVOKEVIRTUAL bnq.b (Lbag;Lbpx;Labp;II)V
   L7
    LINENUMBER 188 L7
    GETSTATIC bdd.j : Lbnq;
    ALOAD 5
    ALOAD 0
    GETFIELD bdd.k : Lazd;
    INVOKEVIRTUAL azd.N ()Lbpx;
    ALOAD 1
    ILOAD 2
    ILOAD 3
    ALOAD 0
    GETFIELD bdd.x : Labp;
    IFNONNULL L8
    ICONST_0
    GOTO L9
   L8
   FRAME FULL [bdd abp I I java/lang/String bag] [bnq bag bpx abp I I]
    BIPUSH 8
   L9
   FRAME FULL [bdd abp I I java/lang/String bag] [bnq bag bpx abp I I I]
    ISUB
    ALOAD 4
    INVOKEVIRTUAL bnq.a (Lbag;Lbpx;Labp;IILjava/lang/String;)V
   L10
    LINENUMBER 189 L10
    ALOAD 0
    FCONST_0
    PUTFIELD bdd.e : F
   L11
    LINENUMBER 190 L11
    GETSTATIC bdd.j : Lbnq;
    FCONST_0
    PUTFIELD bnq.f : F
   L12
    LINENUMBER 191 L12
    RETURN
   L13
    LOCALVARIABLE this Lbdd; L0 L13 0
    LOCALVARIABLE p_146982_1_ Labp; L0 L13 1
    LOCALVARIABLE p_146982_2_ I L0 L13 2
    LOCALVARIABLE p_146982_3_ I L0 L13 3
    LOCALVARIABLE p_146982_4_ Ljava/lang/String; L0 L13 4
    LOCALVARIABLE font Lbag; L4 L13 5
    MAXSTACK = 7
    MAXLOCALS = 6

  // access flags 0x4
  protected b(II)V
   L0
    LINENUMBER 193 L0
    RETURN
   L1
    LOCALVARIABLE this Lbdd; L0 L1 0
    LOCALVARIABLE p_146979_1_ I L0 L1 1
    LOCALVARIABLE p_146979_2_ I L0 L1 2
    MAXSTACK = 0
    MAXLOCALS = 3

  // access flags 0x404
  protected abstract a(FII)V

  // access flags 0x2
  private a(Lzk;)V
   L0
    LINENUMBER 199 L0
    ALOAD 1
    GETFIELD zk.h : I
    ISTORE 2
   L1
    LINENUMBER 200 L1
    ALOAD 1
    GETFIELD zk.i : I
    ISTORE 3
   L2
    LINENUMBER 201 L2
    ALOAD 1
    INVOKEVIRTUAL zk.d ()Labp;
    ASTORE 4
   L3
    LINENUMBER 202 L3
    ICONST_0
    ISTORE 5
   L4
    LINENUMBER 203 L4
    ALOAD 1
    ALOAD 0
    GETFIELD bdd.v : Lzk;
    IF_ACMPNE L5
    ALOAD 0
    GETFIELD bdd.x : Labp;
    IFNULL L5
    ALOAD 0
    GETFIELD bdd.w : Z
    IFNE L5
    ICONST_1
    GOTO L6
   L5
   FRAME FULL [bdd zk I I abp I] []
    ICONST_0
   L6
   FRAME FULL [bdd zk I I abp I] [I]
    ISTORE 6
   L7
    LINENUMBER 204 L7
    ALOAD 0
    GETFIELD bdd.k : Lazd;
    GETFIELD azd.h : Lbje;
    GETFIELD bje.bn : Lxj;
    INVOKEVIRTUAL xj.o ()Labp;
    ASTORE 7
   L8
    LINENUMBER 205 L8
    ACONST_NULL
    ASTORE 8
   L9
    LINENUMBER 207 L9
    ALOAD 1
    ALOAD 0
    GETFIELD bdd.v : Lzk;
    IF_ACMPNE L10
    ALOAD 0
    GETFIELD bdd.x : Labp;
    IFNULL L10
    ALOAD 0
    GETFIELD bdd.w : Z
    IFEQ L10
    ALOAD 4
    IFNULL L10
   L11
    LINENUMBER 209 L11
    ALOAD 4
    INVOKEVIRTUAL abp.m ()Labp;
    ASTORE 4
   L12
    LINENUMBER 210 L12
    ALOAD 4
    DUP
    GETFIELD abp.b : I
    ICONST_2
    IDIV
    PUTFIELD abp.b : I
    GOTO L13
   L10
    LINENUMBER 212 L10
   FRAME FULL [bdd zk I I abp I I abp N] []
    ALOAD 0
    GETFIELD bdd.t : Z
    IFEQ L13
    ALOAD 0
    GETFIELD bdd.s : Ljava/util/Set;
    ALOAD 1
    INVOKEINTERFACE java/util/Set.contains (Ljava/lang/Object;)Z
    IFEQ L13
    ALOAD 7
    IFNULL L13
   L14
    LINENUMBER 214 L14
    ALOAD 0
    GETFIELD bdd.s : Ljava/util/Set;
    INVOKEINTERFACE java/util/Set.size ()I
    ICONST_1
    IF_ICMPNE L15
   L16
    LINENUMBER 216 L16
    RETURN
   L15
    LINENUMBER 219 L15
   FRAME FULL [bdd zk I I abp I I abp N] []
    ALOAD 1
    ALOAD 7
    ICONST_1
    INVOKESTATIC ye.a (Lzk;Labp;Z)Z
    IFEQ L17
    ALOAD 0
    GETFIELD bdd.h : Lye;
    ALOAD 1
    INVOKEVIRTUAL ye.b (Lzk;)Z
    IFEQ L17
   L18
    LINENUMBER 221 L18
    ALOAD 7
    INVOKEVIRTUAL abp.m ()Labp;
    ASTORE 4
   L19
    LINENUMBER 222 L19
    ICONST_1
    ISTORE 5
   L20
    LINENUMBER 223 L20
    ALOAD 0
    GETFIELD bdd.s : Ljava/util/Set;
    ALOAD 0
    GETFIELD bdd.F : I
    ALOAD 4
    ALOAD 1
    INVOKEVIRTUAL zk.d ()Labp;
    IFNONNULL L21
    ICONST_0
    GOTO L22
   L21
   FRAME FULL [bdd zk I I abp I I abp N] [java/util/Set I abp]
    ALOAD 1
    INVOKEVIRTUAL zk.d ()Labp;
    GETFIELD abp.b : I
   L22
   FRAME FULL [bdd zk I I abp I I abp N] [java/util/Set I abp I]
    INVOKESTATIC ye.a (Ljava/util/Set;ILabp;I)V
   L23
    LINENUMBER 225 L23
    ALOAD 4
    GETFIELD abp.b : I
    ALOAD 4
    INVOKEVIRTUAL abp.e ()I
    IF_ICMPLE L24
   L25
    LINENUMBER 227 L25
    NEW java/lang/StringBuilder
    DUP
    INVOKESPECIAL java/lang/StringBuilder.<init> ()V
    GETSTATIC a.o : La;
    INVOKEVIRTUAL java/lang/StringBuilder.append (Ljava/lang/Object;)Ljava/lang/StringBuilder;
    LDC ""
    INVOKEVIRTUAL java/lang/StringBuilder.append (Ljava/lang/String;)Ljava/lang/StringBuilder;
    ALOAD 4
    INVOKEVIRTUAL abp.e ()I
    INVOKEVIRTUAL java/lang/StringBuilder.append (I)Ljava/lang/StringBuilder;
    INVOKEVIRTUAL java/lang/StringBuilder.toString ()Ljava/lang/String;
    ASTORE 8
   L26
    LINENUMBER 228 L26
    ALOAD 4
    ALOAD 4
    INVOKEVIRTUAL abp.e ()I
    PUTFIELD abp.b : I
   L24
    LINENUMBER 231 L24
   FRAME FULL [bdd zk I I abp I I abp java/lang/String] []
    ALOAD 4
    GETFIELD abp.b : I
    ALOAD 1
    INVOKEVIRTUAL zk.a ()I
    IF_ICMPLE L13
   L27
    LINENUMBER 233 L27
    NEW java/lang/StringBuilder
    DUP
    INVOKESPECIAL java/lang/StringBuilder.<init> ()V
    GETSTATIC a.o : La;
    INVOKEVIRTUAL java/lang/StringBuilder.append (Ljava/lang/Object;)Ljava/lang/StringBuilder;
    LDC ""
    INVOKEVIRTUAL java/lang/StringBuilder.append (Ljava/lang/String;)Ljava/lang/StringBuilder;
    ALOAD 1
    INVOKEVIRTUAL zk.a ()I
    INVOKEVIRTUAL java/lang/StringBuilder.append (I)Ljava/lang/StringBuilder;
    INVOKEVIRTUAL java/lang/StringBuilder.toString ()Ljava/lang/String;
    ASTORE 8
   L28
    LINENUMBER 234 L28
    ALOAD 4
    ALOAD 1
    INVOKEVIRTUAL zk.a ()I
    PUTFIELD abp.b : I
    GOTO L13
   L17
    LINENUMBER 239 L17
   FRAME FULL [bdd zk I I abp I I abp N] []
    ALOAD 0
    GETFIELD bdd.s : Ljava/util/Set;
    ALOAD 1
    INVOKEINTERFACE java/util/Set.remove (Ljava/lang/Object;)Z
    POP
   L29
    LINENUMBER 240 L29
    ALOAD 0
    INVOKESPECIAL bdd.g ()V
   L13
    LINENUMBER 244 L13
   FRAME FULL [bdd zk I I abp I I abp java/lang/String] []
    ALOAD 0
    LDC 100.0
    PUTFIELD bdd.e : F
   L30
    LINENUMBER 245 L30
    GETSTATIC bdd.j : Lbnq;
    LDC 100.0
    PUTFIELD bnq.f : F
   L31
    LINENUMBER 247 L31
    ALOAD 4
    IFNONNULL L32
   L33
    LINENUMBER 249 L33
    ALOAD 1
    INVOKEVIRTUAL zk.c ()Lps;
    ASTORE 9
   L34
    LINENUMBER 251 L34
    ALOAD 9
    IFNULL L32
   L35
    LINENUMBER 253 L35
    SIPUSH 2896
    INVOKESTATIC org/lwjgl/opengl/GL11.glDisable (I)V
   L36
    LINENUMBER 254 L36
    ALOAD 0
    GETFIELD bdd.k : Lazd;
    INVOKEVIRTUAL azd.N ()Lbpx;
    GETSTATIC bpr.c : Lbqo;
    INVOKEVIRTUAL bpx.a (Lbqo;)V
   L37
    LINENUMBER 255 L37
    ALOAD 0
    ILOAD 2
    ILOAD 3
    ALOAD 9
    BIPUSH 16
    BIPUSH 16
    INVOKEVIRTUAL bdd.a (IILps;II)V
   L38
    LINENUMBER 256 L38
    SIPUSH 2896
    INVOKESTATIC org/lwjgl/opengl/GL11.glEnable (I)V
   L39
    LINENUMBER 257 L39
    ICONST_1
    ISTORE 6
   L32
    LINENUMBER 261 L32
   FRAME FULL [bdd zk I I abp I I abp java/lang/String] []
    ILOAD 6
    IFNE L40
   L41
    LINENUMBER 263 L41
    ILOAD 5
    IFEQ L42
   L43
    LINENUMBER 265 L43
    ILOAD 2
    ILOAD 3
    ILOAD 2
    BIPUSH 16
    IADD
    ILOAD 3
    BIPUSH 16
    IADD
    LDC -2130706433
    INVOKESTATIC bdd.a (IIIII)V
   L42
    LINENUMBER 268 L42
   FRAME FULL [bdd zk I I abp I I abp java/lang/String] []
    SIPUSH 2929
    INVOKESTATIC org/lwjgl/opengl/GL11.glEnable (I)V
    ALOAD 0
    GETFIELD bdd.manager : Lcodechicken/nei/guihook/GuiContainerManager;
    ALOAD 1
    INVOKEVIRTUAL codechicken/nei/guihook/GuiContainerManager.renderSlotUnderlay (Lnet/minecraft/inventory/Slot;)V
    ALOAD 0
    GETFIELD bdd.manager : Lcodechicken/nei/guihook/GuiContainerManager;
    ALOAD 1
    ALOAD 4
    ILOAD 2
    ILOAD 3
    ALOAD 8
    INVOKEVIRTUAL codechicken/nei/guihook/GuiContainerManager.drawSlotItem (Lnet/minecraft/inventory/Slot;Lnet/minecraft/item/ItemStack;IILjava/lang/String;)V
    ALOAD 0
    GETFIELD bdd.manager : Lcodechicken/nei/guihook/GuiContainerManager;
    ALOAD 1
    INVOKEVIRTUAL codechicken/nei/guihook/GuiContainerManager.renderSlotOverlay (Lnet/minecraft/inventory/Slot;)V
   L40
    LINENUMBER 273 L40
   FRAME FULL [bdd zk I I abp I I abp java/lang/String] []
    GETSTATIC bdd.j : Lbnq;
    FCONST_0
    PUTFIELD bnq.f : F
   L44
    LINENUMBER 274 L44
    ALOAD 0
    FCONST_0
    PUTFIELD bdd.e : F
   L45
    LINENUMBER 275 L45
    RETURN
   L46
    LOCALVARIABLE iicon Lps; L34 L32 9
    LOCALVARIABLE this Lbdd; L0 L46 0
    LOCALVARIABLE p_146977_1_ Lzk; L0 L46 1
    LOCALVARIABLE i I L1 L46 2
    LOCALVARIABLE j I L2 L46 3
    LOCALVARIABLE itemstack Labp; L3 L46 4
    LOCALVARIABLE flag Z L4 L46 5
    LOCALVARIABLE flag1 Z L7 L46 6
    LOCALVARIABLE itemstack1 Labp; L8 L46 7
    LOCALVARIABLE s Ljava/lang/String; L9 L46 8
    MAXSTACK = 6
    MAXLOCALS = 10

  // access flags 0x2
  private g()V
   L0
    LINENUMBER 279 L0
    ALOAD 0
    GETFIELD bdd.k : Lazd;
    GETFIELD azd.h : Lbje;
    GETFIELD bje.bn : Lxj;
    INVOKEVIRTUAL xj.o ()Labp;
    ASTORE 1
   L1
    LINENUMBER 281 L1
    ALOAD 1
    IFNULL L2
    ALOAD 0
    GETFIELD bdd.t : Z
    IFEQ L2
   L3
    LINENUMBER 283 L3
    ALOAD 0
    ALOAD 1
    GETFIELD abp.b : I
    PUTFIELD bdd.I : I
   L4
    LINENUMBER 287 L4
    ALOAD 0
    GETFIELD bdd.s : Ljava/util/Set;
    INVOKEINTERFACE java/util/Set.iterator ()Ljava/util/Iterator;
    ASTORE 4
   L5
   FRAME FULL [bdd abp T T java/util/Iterator] []
    ALOAD 4
    INVOKEINTERFACE java/util/Iterator.hasNext ()Z
    IFEQ L2
   L6
    LINENUMBER 289 L6
    ALOAD 4
    INVOKEINTERFACE java/util/Iterator.next ()Ljava/lang/Object;
    CHECKCAST zk
    ASTORE 5
   L7
    LINENUMBER 290 L7
    ALOAD 1
    INVOKEVIRTUAL abp.m ()Labp;
    ASTORE 2
   L8
    LINENUMBER 291 L8
    ALOAD 5
    INVOKEVIRTUAL zk.d ()Labp;
    IFNONNULL L9
    ICONST_0
    GOTO L10
   L9
   FRAME FULL [bdd abp abp T java/util/Iterator zk] []
    ALOAD 5
    INVOKEVIRTUAL zk.d ()Labp;
    GETFIELD abp.b : I
   L10
   FRAME FULL [bdd abp abp T java/util/Iterator zk] [I]
    ISTORE 3
   L11
    LINENUMBER 292 L11
    ALOAD 0
    GETFIELD bdd.s : Ljava/util/Set;
    ALOAD 0
    GETFIELD bdd.F : I
    ALOAD 2
    ILOAD 3
    INVOKESTATIC ye.a (Ljava/util/Set;ILabp;I)V
   L12
    LINENUMBER 294 L12
    ALOAD 2
    GETFIELD abp.b : I
    ALOAD 2
    INVOKEVIRTUAL abp.e ()I
    IF_ICMPLE L13
   L14
    LINENUMBER 296 L14
    ALOAD 2
    ALOAD 2
    INVOKEVIRTUAL abp.e ()I
    PUTFIELD abp.b : I
   L13
    LINENUMBER 299 L13
   FRAME FULL [bdd abp abp I java/util/Iterator zk] []
    ALOAD 2
    GETFIELD abp.b : I
    ALOAD 5
    INVOKEVIRTUAL zk.a ()I
    IF_ICMPLE L15
   L16
    LINENUMBER 301 L16
    ALOAD 2
    ALOAD 5
    INVOKEVIRTUAL zk.a ()I
    PUTFIELD abp.b : I
   L15
    LINENUMBER 287 L15
   FRAME FULL [bdd abp abp I java/util/Iterator zk] []
    ALOAD 0
    DUP
    GETFIELD bdd.I : I
    ALOAD 2
    GETFIELD abp.b : I
    ILOAD 3
    ISUB
    ISUB
    PUTFIELD bdd.I : I
    GOTO L5
   L2
    LINENUMBER 305 L2
   FRAME FULL [bdd abp] []
    RETURN
   L17
    LOCALVARIABLE slot Lzk; L7 L15 5
    LOCALVARIABLE itemstack1 Labp; L8 L2 2
    LOCALVARIABLE i I L11 L2 3
    LOCALVARIABLE iterator Ljava/util/Iterator; L5 L2 4
    LOCALVARIABLE this Lbdd; L0 L17 0
    LOCALVARIABLE itemstack Labp; L1 L17 1
    MAXSTACK = 4
    MAXLOCALS = 6

  // access flags 0x2
  private c(II)Lzk;
   L0
    LINENUMBER 309 L0
    ICONST_0
    ISTORE 3
   L1
   FRAME FULL [bdd I I I] []
    ILOAD 3
    ALOAD 0
    GETFIELD bdd.h : Lye;
    GETFIELD ye.c : Ljava/util/List;
    INVOKEINTERFACE java/util/List.size ()I
    IF_ICMPGE L2
   L3
    LINENUMBER 311 L3
    ALOAD 0
    GETFIELD bdd.h : Lye;
    GETFIELD ye.c : Ljava/util/List;
    ILOAD 3
    INVOKEINTERFACE java/util/List.get (I)Ljava/lang/Object;
    CHECKCAST zk
    ASTORE 4
   L4
    LINENUMBER 313 L4
    ALOAD 0
    ALOAD 4
    ILOAD 1
    ILOAD 2
    INVOKESPECIAL bdd.a (Lzk;II)Z
    IFEQ L5
   L6
    LINENUMBER 315 L6
    ALOAD 4
    ARETURN
   L5
    LINENUMBER 309 L5
   FRAME FULL [bdd I I I zk] []
    IINC 3 1
    GOTO L1
   L2
    LINENUMBER 319 L2
   FRAME FULL [bdd I I I] []
    ACONST_NULL
    ARETURN
   L7
    LOCALVARIABLE slot Lzk; L4 L5 4
    LOCALVARIABLE k I L1 L2 3
    LOCALVARIABLE this Lbdd; L0 L7 0
    LOCALVARIABLE p_146975_1_ I L0 L7 1
    LOCALVARIABLE p_146975_2_ I L0 L7 2
    MAXSTACK = 4
    MAXLOCALS = 5

  // access flags 0x4
  protected a(III)V
    ALOAD 0
    GETFIELD bdd.manager : Lcodechicken/nei/guihook/GuiContainerManager;
    ILOAD 1
    ILOAD 2
    ILOAD 3
    INVOKEVIRTUAL codechicken/nei/guihook/GuiContainerManager.mouseClicked (III)Z
    IFEQ L0
    RETURN
   L0
    LINENUMBER 324 L0
   FRAME FULL [bdd I I I] []
    ALOAD 0
    ILOAD 1
    ILOAD 2
    ILOAD 3
    INVOKESPECIAL bcd.a (III)V
   L1
    LINENUMBER 325 L1
    ILOAD 3
    ALOAD 0
    GETFIELD bdd.k : Lazd;
    GETFIELD azd.u : Lazw;
    GETFIELD azw.U : Laza;
    INVOKEVIRTUAL aza.i ()I
    BIPUSH 100
    IADD
    IF_ICMPNE L2
    ICONST_1
    GOTO L3
   L2
   FRAME FULL [bdd I I I] []
    ICONST_0
   L3
   FRAME FULL [bdd I I I] [I]
    ISTORE 4
   L4
    LINENUMBER 326 L4
    ALOAD 0
    ILOAD 1
    ILOAD 2
    INVOKESPECIAL bdd.c (II)Lzk;
    ASTORE 5
   L5
    LINENUMBER 327 L5
    INVOKESTATIC azd.J ()J
    LSTORE 6
   L6
    LINENUMBER 328 L6
    ALOAD 0
    ALOAD 0
    GETFIELD bdd.K : Lzk;
    ALOAD 5
    IF_ACMPNE L7
    LLOAD 6
    ALOAD 0
    GETFIELD bdd.J : J
    LSUB
    LDC 250
    LCMP
    IFGE L7
    ALOAD 0
    GETFIELD bdd.L : I
    ILOAD 3
    IF_ICMPNE L7
    ICONST_1
    GOTO L8
   L7
   FRAME FULL [bdd I I I I zk J] [bdd]
    ICONST_0
   L8
   FRAME FULL [bdd I I I I zk J] [bdd I]
    PUTFIELD bdd.M : Z
   L9
    LINENUMBER 329 L9
    ALOAD 0
    ICONST_0
    PUTFIELD bdd.H : Z
   L10
    LINENUMBER 331 L10
    ILOAD 3
    IFEQ L11
    ILOAD 3
    ICONST_1
    IF_ICMPEQ L11
    ILOAD 4
    IFEQ L12
   L11
    LINENUMBER 333 L11
   FRAME FULL [bdd I I I I zk J] []
    ALOAD 0
    GETFIELD bdd.i : I
    ISTORE 8
   L13
    LINENUMBER 334 L13
    ALOAD 0
    GETFIELD bdd.r : I
    ISTORE 9
   L14
    LINENUMBER 335 L14
    ILOAD 1
    ILOAD 8
    IF_ICMPLT L15
    ILOAD 2
    ILOAD 9
    IF_ICMPLT L15
    ILOAD 1
    ILOAD 8
    ALOAD 0
    GETFIELD bdd.f : I
    IADD
    IF_ICMPGE L15
    ILOAD 2
    ILOAD 9
    ALOAD 0
    GETFIELD bdd.g : I
    IADD
    IF_ICMPLT L16
   L15
   FRAME FULL [bdd I I I I zk J I I] []
    ICONST_1
    GOTO L17
   L16
   FRAME FULL [bdd I I I I zk J I I] []
    ICONST_0
   L17
   FRAME FULL [bdd I I I I zk J I I] [I]
    ISTORE 10
   L18
    LINENUMBER 336 L18
    ICONST_M1
    ISTORE 11
   L19
    LINENUMBER 338 L19
    ALOAD 5
    IFNULL L20
   L21
    LINENUMBER 340 L21
    ALOAD 5
    GETFIELD zk.g : I
    ISTORE 11
   L20
    LINENUMBER 343 L20
   FRAME FULL [bdd I I I I zk J I I I I] []
    ILOAD 10
    IFEQ L22
   L23
    LINENUMBER 345 L23
    SIPUSH -999
    ISTORE 11
   L22
    LINENUMBER 348 L22
   FRAME FULL [bdd I I I I zk J I I I I] []
    ALOAD 0
    GETFIELD bdd.k : Lazd;
    GETFIELD azd.u : Lazw;
    GETFIELD azw.z : Z
    IFEQ L24
    ILOAD 10
    IFEQ L24
    ALOAD 0
    GETFIELD bdd.k : Lazd;
    GETFIELD azd.h : Lbje;
    GETFIELD bje.bn : Lxj;
    INVOKEVIRTUAL xj.o ()Labp;
    IFNONNULL L24
   L25
    LINENUMBER 350 L25
    ALOAD 0
    GETFIELD bdd.k : Lazd;
    ACONST_NULL
    CHECKCAST bcd
    INVOKEVIRTUAL azd.a (Lbcd;)V
   L26
    LINENUMBER 351 L26
    RETURN
   L24
    LINENUMBER 354 L24
   FRAME FULL [bdd I I I I zk J I I I I] []
    ILOAD 11
    ICONST_M1
    IF_ICMPEQ L12
   L27
    LINENUMBER 356 L27
    ALOAD 0
    GETFIELD bdd.k : Lazd;
    GETFIELD azd.u : Lazw;
    GETFIELD azw.z : Z
    IFEQ L28
   L29
    LINENUMBER 358 L29
    ALOAD 5
    IFNULL L30
    ALOAD 5
    INVOKEVIRTUAL zk.e ()Z
    IFEQ L30
   L31
    LINENUMBER 360 L31
    ALOAD 0
    ALOAD 5
    PUTFIELD bdd.v : Lzk;
   L32
    LINENUMBER 361 L32
    ALOAD 0
    ACONST_NULL
    PUTFIELD bdd.x : Labp;
   L33
    LINENUMBER 362 L33
    ALOAD 0
    ILOAD 3
    ICONST_1
    IF_ICMPNE L34
    ICONST_1
    GOTO L35
   L34
   FRAME FULL [bdd I I I I zk J I I I I] [bdd]
    ICONST_0
   L35
   FRAME FULL [bdd I I I I zk J I I I I] [bdd I]
    PUTFIELD bdd.w : Z
    GOTO L12
   L30
    LINENUMBER 366 L30
   FRAME FULL [bdd I I I I zk J I I I I] []
    ALOAD 0
    ACONST_NULL
    PUTFIELD bdd.v : Lzk;
    GOTO L12
   L28
    LINENUMBER 369 L28
   FRAME FULL [bdd I I I I zk J I I I I] []
    ALOAD 0
    GETFIELD bdd.t : Z
    IFNE L12
   L36
    LINENUMBER 371 L36
    ALOAD 0
    GETFIELD bdd.k : Lazd;
    GETFIELD azd.h : Lbje;
    GETFIELD bje.bn : Lxj;
    INVOKEVIRTUAL xj.o ()Labp;
    IFNONNULL L37
   L38
    LINENUMBER 373 L38
    ILOAD 3
    ALOAD 0
    GETFIELD bdd.k : Lazd;
    GETFIELD azd.u : Lazw;
    GETFIELD azw.U : Laza;
    INVOKEVIRTUAL aza.i ()I
    BIPUSH 100
    IADD
    IF_ICMPNE L39
   L40
    LINENUMBER 375 L40
    ALOAD 0
    ALOAD 5
    ILOAD 11
    ILOAD 3
    ICONST_3
    INVOKEVIRTUAL bdd.managerHandleMouseClick (Lzk;III)V
    GOTO L41
   L39
    LINENUMBER 379 L39
   FRAME FULL [bdd I I I I zk J I I I I] []
    ILOAD 11
    SIPUSH -999
    IF_ICMPEQ L42
    BIPUSH 42
    INVOKESTATIC org/lwjgl/input/Keyboard.isKeyDown (I)Z
    IFNE L43
    BIPUSH 54
    INVOKESTATIC org/lwjgl/input/Keyboard.isKeyDown (I)Z
    IFEQ L42
   L43
   FRAME FULL [bdd I I I I zk J I I I I] []
    ICONST_1
    GOTO L44
   L42
   FRAME FULL [bdd I I I I zk J I I I I] []
    ICONST_0
   L44
   FRAME FULL [bdd I I I I zk J I I I I] [I]
    ISTORE 12
   L45
    LINENUMBER 380 L45
    ICONST_0
    ISTORE 13
   L46
    LINENUMBER 382 L46
    ILOAD 12
    IFEQ L47
   L48
    LINENUMBER 384 L48
    ALOAD 0
    ALOAD 5
    IFNULL L49
    ALOAD 5
    INVOKEVIRTUAL zk.e ()Z
    IFEQ L49
    ALOAD 5
    INVOKEVIRTUAL zk.d ()Labp;
    GOTO L50
   L49
   FRAME FULL [bdd I I I I zk J I I I I I I] [bdd]
    ACONST_NULL
   L50
   FRAME FULL [bdd I I I I zk J I I I I I I] [bdd abp]
    PUTFIELD bdd.N : Labp;
   L51
    LINENUMBER 385 L51
    ICONST_1
    ISTORE 13
    GOTO L52
   L47
    LINENUMBER 387 L47
   FRAME FULL [bdd I I I I zk J I I I I I I] []
    ILOAD 11
    SIPUSH -999
    IF_ICMPNE L52
   L53
    LINENUMBER 389 L53
    ICONST_4
    ISTORE 13
   L52
    LINENUMBER 392 L52
   FRAME FULL [bdd I I I I zk J I I I I I I] []
    ALOAD 0
    ALOAD 5
    ILOAD 11
    ILOAD 3
    ILOAD 13
    INVOKEVIRTUAL bdd.managerHandleMouseClick (Lzk;III)V
   L41
    LINENUMBER 395 L41
   FRAME FULL [bdd I I I I zk J I I I I] []
    ALOAD 0
    ICONST_1
    PUTFIELD bdd.H : Z
    GOTO L12
   L37
    LINENUMBER 399 L37
   FRAME FULL [bdd I I I I zk J I I I I] []
    ALOAD 0
    ICONST_1
    PUTFIELD bdd.t : Z
   L54
    LINENUMBER 400 L54
    ALOAD 0
    ILOAD 3
    PUTFIELD bdd.G : I
   L55
    LINENUMBER 401 L55
    ALOAD 0
    GETFIELD bdd.s : Ljava/util/Set;
    INVOKEINTERFACE java/util/Set.clear ()V
   L56
    LINENUMBER 403 L56
    ILOAD 3
    IFNE L57
   L58
    LINENUMBER 405 L58
    ALOAD 0
    ICONST_0
    PUTFIELD bdd.F : I
    GOTO L12
   L57
    LINENUMBER 407 L57
   FRAME FULL [bdd I I I I zk J I I I I] []
    ILOAD 3
    ICONST_1
    IF_ICMPNE L12
   L59
    LINENUMBER 409 L59
    ALOAD 0
    ICONST_1
    PUTFIELD bdd.F : I
   L12
    LINENUMBER 416 L12
   FRAME FULL [bdd I I I I zk J] []
    ALOAD 0
    ALOAD 5
    PUTFIELD bdd.K : Lzk;
   L60
    LINENUMBER 417 L60
    ALOAD 0
    LLOAD 6
    PUTFIELD bdd.J : J
   L61
    LINENUMBER 418 L61
    ALOAD 0
    ILOAD 3
    PUTFIELD bdd.L : I
   L62
    LINENUMBER 419 L62
    RETURN
   L63
    LOCALVARIABLE flag2 Z L45 L41 12
    LOCALVARIABLE b0 B L46 L41 13
    LOCALVARIABLE i1 I L13 L12 8
    LOCALVARIABLE j1 I L14 L12 9
    LOCALVARIABLE flag1 Z L18 L12 10
    LOCALVARIABLE k1 I L19 L12 11
    LOCALVARIABLE this Lbdd; L0 L63 0
    LOCALVARIABLE par1 I L0 L63 1
    LOCALVARIABLE par2 I L0 L63 2
    LOCALVARIABLE par3 I L0 L63 3
    LOCALVARIABLE flag Z L4 L63 4
    LOCALVARIABLE slot Lzk; L5 L63 5
    LOCALVARIABLE l J L6 L63 6
    MAXSTACK = 5
    MAXLOCALS = 14

  // access flags 0x4
  protected a(IIIJ)V
   L0
    LINENUMBER 423 L0
    ALOAD 0
    ILOAD 1
    ILOAD 2
    INVOKESPECIAL bdd.c (II)Lzk;
    ASTORE 6
   L1
    LINENUMBER 424 L1
    ALOAD 0
    GETFIELD bdd.k : Lazd;
    GETFIELD azd.h : Lbje;
    GETFIELD bje.bn : Lxj;
    INVOKEVIRTUAL xj.o ()Labp;
    ASTORE 7
    ALOAD 0
    GETFIELD bdd.manager : Lcodechicken/nei/guihook/GuiContainerManager;
    ILOAD 1
    ILOAD 2
    ILOAD 3
    LLOAD 4
    INVOKEVIRTUAL codechicken/nei/guihook/GuiContainerManager.mouseDragged (IIIJ)V
   L2
    LINENUMBER 426 L2
    ALOAD 0
    GETFIELD bdd.v : Lzk;
    IFNULL L3
    ALOAD 0
    GETFIELD bdd.k : Lazd;
    GETFIELD azd.u : Lazw;
    GETFIELD azw.z : Z
    IFEQ L3
   L4
    LINENUMBER 428 L4
    ILOAD 3
    IFEQ L5
    ILOAD 3
    ICONST_1
    IF_ICMPNE L6
   L5
    LINENUMBER 430 L5
   FRAME FULL [bdd I I I J zk abp] []
    ALOAD 0
    GETFIELD bdd.x : Labp;
    IFNONNULL L7
   L8
    LINENUMBER 432 L8
    ALOAD 6
    ALOAD 0
    GETFIELD bdd.v : Lzk;
    IF_ACMPEQ L6
   L9
    LINENUMBER 434 L9
    ALOAD 0
    ALOAD 0
    GETFIELD bdd.v : Lzk;
    INVOKEVIRTUAL zk.d ()Labp;
    INVOKEVIRTUAL abp.m ()Labp;
    PUTFIELD bdd.x : Labp;
    GOTO L6
   L7
    LINENUMBER 437 L7
   FRAME FULL [bdd I I I J zk abp] []
    ALOAD 0
    GETFIELD bdd.x : Labp;
    GETFIELD abp.b : I
    ICONST_1
    IF_ICMPLE L6
    ALOAD 6
    IFNULL L6
    ALOAD 6
    ALOAD 0
    GETFIELD bdd.x : Labp;
    ICONST_0
    INVOKESTATIC ye.a (Lzk;Labp;Z)Z
    IFEQ L6
   L10
    LINENUMBER 439 L10
    INVOKESTATIC azd.J ()J
    LSTORE 8
   L11
    LINENUMBER 441 L11
    ALOAD 0
    GETFIELD bdd.D : Lzk;
    ALOAD 6
    IF_ACMPNE L12
   L13
    LINENUMBER 443 L13
    LLOAD 8
    ALOAD 0
    GETFIELD bdd.E : J
    LSUB
    LDC 500
    LCMP
    IFLE L14
   L15
    LINENUMBER 445 L15
    ALOAD 0
    ALOAD 0
    GETFIELD bdd.v : Lzk;
    ALOAD 0
    GETFIELD bdd.v : Lzk;
    GETFIELD zk.g : I
    ICONST_0
    ICONST_0
    INVOKEVIRTUAL bdd.managerHandleMouseClick (Lzk;III)V
   L16
    LINENUMBER 446 L16
    ALOAD 0
    ALOAD 6
    ALOAD 6
    GETFIELD zk.g : I
    ICONST_1
    ICONST_0
    INVOKEVIRTUAL bdd.managerHandleMouseClick (Lzk;III)V
   L17
    LINENUMBER 447 L17
    ALOAD 0
    ALOAD 0
    GETFIELD bdd.v : Lzk;
    ALOAD 0
    GETFIELD bdd.v : Lzk;
    GETFIELD zk.g : I
    ICONST_0
    ICONST_0
    INVOKEVIRTUAL bdd.managerHandleMouseClick (Lzk;III)V
   L18
    LINENUMBER 448 L18
    ALOAD 0
    LLOAD 8
    LDC 750
    LADD
    PUTFIELD bdd.E : J
   L19
    LINENUMBER 449 L19
    ALOAD 0
    GETFIELD bdd.x : Labp;
    DUP
    GETFIELD abp.b : I
    ICONST_1
    ISUB
    PUTFIELD abp.b : I
    GOTO L14
   L12
    LINENUMBER 454 L12
   FRAME FULL [bdd I I I J zk abp J] []
    ALOAD 0
    ALOAD 6
    PUTFIELD bdd.D : Lzk;
   L20
    LINENUMBER 455 L20
    ALOAD 0
    LLOAD 8
    PUTFIELD bdd.E : J
   L14
    LINENUMBER 457 L14
   FRAME FULL [bdd I I I J zk abp J] []
    GOTO L6
   L3
    LINENUMBER 460 L3
   FRAME FULL [bdd I I I J zk abp] []
    ALOAD 0
    GETFIELD bdd.t : Z
    IFEQ L6
    ALOAD 6
    IFNULL L6
    ALOAD 7
    IFNULL L6
    ALOAD 7
    GETFIELD abp.b : I
    ALOAD 0
    GETFIELD bdd.s : Ljava/util/Set;
    INVOKEINTERFACE java/util/Set.size ()I
    IF_ICMPLE L6
    ALOAD 6
    ALOAD 7
    ICONST_1
    INVOKESTATIC ye.a (Lzk;Labp;Z)Z
    IFEQ L6
    ALOAD 6
    ALOAD 7
    INVOKEVIRTUAL zk.a (Labp;)Z
    IFEQ L6
    ALOAD 0
    GETFIELD bdd.h : Lye;
    ALOAD 6
    INVOKEVIRTUAL ye.b (Lzk;)Z
    IFEQ L6
   L21
    LINENUMBER 462 L21
    ALOAD 0
    GETFIELD bdd.s : Ljava/util/Set;
    ALOAD 6
    INVOKEINTERFACE java/util/Set.add (Ljava/lang/Object;)Z
    POP
   L22
    LINENUMBER 463 L22
    ALOAD 0
    INVOKESPECIAL bdd.g ()V
   L6
    LINENUMBER 465 L6
   FRAME FULL [bdd I I I J zk abp] []
    RETURN
   L23
    LOCALVARIABLE i1 J L11 L14 8
    LOCALVARIABLE this Lbdd; L0 L23 0
    LOCALVARIABLE p_146273_1_ I L0 L23 1
    LOCALVARIABLE p_146273_2_ I L0 L23 2
    LOCALVARIABLE p_146273_3_ I L0 L23 3
    LOCALVARIABLE p_146273_4_ J L0 L23 4
    LOCALVARIABLE slot Lzk; L1 L23 6
    LOCALVARIABLE itemstack Labp; L2 L23 7
    MAXSTACK = 6
    MAXLOCALS = 10

  // access flags 0x4
  protected b(III)V
    ALOAD 0
    GETFIELD bdd.manager : Lcodechicken/nei/guihook/GuiContainerManager;
    ILOAD 1
    ILOAD 2
    ILOAD 3
    INVOKEVIRTUAL codechicken/nei/guihook/GuiContainerManager.overrideMouseUp (III)Z
    IFEQ L0
    RETURN
   L0
    LINENUMBER 469 L0
   FRAME FULL [bdd I I I] []
    ALOAD 0
    ILOAD 1
    ILOAD 2
    ILOAD 3
    INVOKESPECIAL bcd.b (III)V
   L1
    LINENUMBER 470 L1
    ALOAD 0
    ILOAD 1
    ILOAD 2
    INVOKESPECIAL bdd.c (II)Lzk;
    ASTORE 4
   L2
    LINENUMBER 471 L2
    ALOAD 0
    GETFIELD bdd.i : I
    ISTORE 5
   L3
    LINENUMBER 472 L3
    ALOAD 0
    GETFIELD bdd.r : I
    ISTORE 6
   L4
    LINENUMBER 473 L4
    ILOAD 1
    ILOAD 5
    IF_ICMPLT L5
    ILOAD 2
    ILOAD 6
    IF_ICMPLT L5
    ILOAD 1
    ILOAD 5
    ALOAD 0
    GETFIELD bdd.f : I
    IADD
    IF_ICMPGE L5
    ILOAD 2
    ILOAD 6
    ALOAD 0
    GETFIELD bdd.g : I
    IADD
    IF_ICMPLT L6
   L5
   FRAME FULL [bdd I I I zk I I] []
    ICONST_1
    GOTO L7
   L6
   FRAME FULL [bdd I I I zk I I] []
    ICONST_0
   L7
   FRAME FULL [bdd I I I zk I I] [I]
    ISTORE 7
   L8
    LINENUMBER 474 L8
    ICONST_M1
    ISTORE 8
   L9
    LINENUMBER 476 L9
    ALOAD 4
    IFNULL L10
   L11
    LINENUMBER 478 L11
    ALOAD 4
    GETFIELD zk.g : I
    ISTORE 8
   L10
    LINENUMBER 481 L10
   FRAME FULL [bdd I I I zk I I I I] []
    ILOAD 7
    IFEQ L12
   L13
    LINENUMBER 483 L13
    SIPUSH -999
    ISTORE 8
   L12
    LINENUMBER 489 L12
   FRAME FULL [bdd I I I zk I I I I] []
    ALOAD 0
    GETFIELD bdd.M : Z
    IFEQ L14
    ALOAD 4
    IFNULL L14
    ILOAD 3
    IFNE L14
    ALOAD 0
    GETFIELD bdd.h : Lye;
    ACONST_NULL
    CHECKCAST abp
    ALOAD 4
    INVOKEVIRTUAL ye.a (Labp;Lzk;)Z
    IFEQ L14
   L15
    LINENUMBER 491 L15
    INVOKESTATIC bdd.n ()Z
    IFEQ L16
   L17
    LINENUMBER 493 L17
    ALOAD 4
    IFNULL L18
    ALOAD 4
    GETFIELD zk.f : Lpo;
    IFNULL L18
    ALOAD 0
    GETFIELD bdd.N : Labp;
    IFNULL L18
   L19
    LINENUMBER 495 L19
    ALOAD 0
    GETFIELD bdd.h : Lye;
    GETFIELD ye.c : Ljava/util/List;
    INVOKEINTERFACE java/util/List.iterator ()Ljava/util/Iterator;
    ASTORE 9
   L20
    LINENUMBER 497 L20
   FRAME FULL [bdd I I I zk I I I I java/util/Iterator] []
    ALOAD 9
    INVOKEINTERFACE java/util/Iterator.hasNext ()Z
    IFEQ L18
   L21
    LINENUMBER 499 L21
    ALOAD 9
    INVOKEINTERFACE java/util/Iterator.next ()Ljava/lang/Object;
    CHECKCAST zk
    ASTORE 10
   L22
    LINENUMBER 501 L22
    ALOAD 10
    IFNULL L20
    ALOAD 10
    ALOAD 0
    GETFIELD bdd.k : Lazd;
    GETFIELD azd.h : Lbje;
    INVOKEVIRTUAL zk.a (Lxl;)Z
    IFEQ L20
    ALOAD 10
    INVOKEVIRTUAL zk.e ()Z
    IFEQ L20
    ALOAD 10
    GETFIELD zk.f : Lpo;
    ALOAD 4
    GETFIELD zk.f : Lpo;
    IF_ACMPNE L20
    ALOAD 10
    ALOAD 0
    GETFIELD bdd.N : Labp;
    ICONST_1
    INVOKESTATIC ye.a (Lzk;Labp;Z)Z
    IFEQ L20
   L23
    LINENUMBER 503 L23
    ALOAD 0
    ALOAD 10
    ALOAD 10
    GETFIELD zk.g : I
    ILOAD 3
    ICONST_1
    INVOKEVIRTUAL bdd.managerHandleMouseClick (Lzk;III)V
    GOTO L20
   L16
    LINENUMBER 510 L16
   FRAME FULL [bdd I I I zk I I I I] []
    ALOAD 0
    ALOAD 4
    ILOAD 8
    ILOAD 3
    BIPUSH 6
    INVOKEVIRTUAL bdd.managerHandleMouseClick (Lzk;III)V
   L18
    LINENUMBER 513 L18
   FRAME FULL [bdd I I I zk I I I I] []
    ALOAD 0
    ICONST_0
    PUTFIELD bdd.M : Z
   L24
    LINENUMBER 514 L24
    ALOAD 0
    LCONST_0
    PUTFIELD bdd.J : J
    GOTO L25
   L14
    LINENUMBER 518 L14
   FRAME FULL [bdd I I I zk I I I I] []
    ALOAD 0
    GETFIELD bdd.t : Z
    IFEQ L26
    ALOAD 0
    GETFIELD bdd.G : I
    ILOAD 3
    IF_ICMPEQ L26
   L27
    LINENUMBER 520 L27
    ALOAD 0
    ICONST_0
    PUTFIELD bdd.t : Z
   L28
    LINENUMBER 521 L28
    ALOAD 0
    GETFIELD bdd.s : Ljava/util/Set;
    INVOKEINTERFACE java/util/Set.clear ()V
   L29
    LINENUMBER 522 L29
    ALOAD 0
    ICONST_1
    PUTFIELD bdd.H : Z
   L30
    LINENUMBER 523 L30
    RETURN
   L26
    LINENUMBER 526 L26
   FRAME FULL [bdd I I I zk I I I I] []
    ALOAD 0
    GETFIELD bdd.H : Z
    IFEQ L31
   L32
    LINENUMBER 528 L32
    ALOAD 0
    ICONST_0
    PUTFIELD bdd.H : Z
   L33
    LINENUMBER 529 L33
    RETURN
   L31
    LINENUMBER 534 L31
   FRAME FULL [bdd I I I zk I I I I] []
    ALOAD 0
    GETFIELD bdd.v : Lzk;
    IFNULL L34
    ALOAD 0
    GETFIELD bdd.k : Lazd;
    GETFIELD azd.u : Lazw;
    GETFIELD azw.z : Z
    IFEQ L34
   L35
    LINENUMBER 536 L35
    ILOAD 3
    IFEQ L36
    ILOAD 3
    ICONST_1
    IF_ICMPNE L25
   L36
    LINENUMBER 538 L36
   FRAME FULL [bdd I I I zk I I I I] []
    ALOAD 0
    GETFIELD bdd.x : Labp;
    IFNONNULL L37
    ALOAD 4
    ALOAD 0
    GETFIELD bdd.v : Lzk;
    IF_ACMPEQ L37
   L38
    LINENUMBER 540 L38
    ALOAD 0
    ALOAD 0
    GETFIELD bdd.v : Lzk;
    INVOKEVIRTUAL zk.d ()Labp;
    PUTFIELD bdd.x : Labp;
   L37
    LINENUMBER 543 L37
   FRAME FULL [bdd I I I zk I I I I] []
    ALOAD 4
    ALOAD 0
    GETFIELD bdd.x : Labp;
    ICONST_0
    INVOKESTATIC ye.a (Lzk;Labp;Z)Z
    ISTORE 11
   L39
    LINENUMBER 545 L39
    ILOAD 8
    ICONST_M1
    IF_ICMPEQ L40
    ALOAD 0
    GETFIELD bdd.x : Labp;
    IFNULL L40
    ILOAD 11
    IFEQ L40
   L41
    LINENUMBER 547 L41
    ALOAD 0
    ALOAD 0
    GETFIELD bdd.v : Lzk;
    ALOAD 0
    GETFIELD bdd.v : Lzk;
    GETFIELD zk.g : I
    ILOAD 3
    ICONST_0
    INVOKEVIRTUAL bdd.managerHandleMouseClick (Lzk;III)V
   L42
    LINENUMBER 548 L42
    ALOAD 0
    ALOAD 4
    ILOAD 8
    ICONST_0
    ICONST_0
    INVOKEVIRTUAL bdd.managerHandleMouseClick (Lzk;III)V
   L43
    LINENUMBER 550 L43
    ALOAD 0
    GETFIELD bdd.k : Lazd;
    GETFIELD azd.h : Lbje;
    GETFIELD bje.bn : Lxj;
    INVOKEVIRTUAL xj.o ()Labp;
    IFNULL L44
   L45
    LINENUMBER 552 L45
    ALOAD 0
    ALOAD 0
    GETFIELD bdd.v : Lzk;
    ALOAD 0
    GETFIELD bdd.v : Lzk;
    GETFIELD zk.g : I
    ILOAD 3
    ICONST_0
    INVOKEVIRTUAL bdd.managerHandleMouseClick (Lzk;III)V
   L46
    LINENUMBER 553 L46
    ALOAD 0
    ILOAD 1
    ILOAD 5
    ISUB
    PUTFIELD bdd.y : I
   L47
    LINENUMBER 554 L47
    ALOAD 0
    ILOAD 2
    ILOAD 6
    ISUB
    PUTFIELD bdd.z : I
   L48
    LINENUMBER 555 L48
    ALOAD 0
    ALOAD 0
    GETFIELD bdd.v : Lzk;
    PUTFIELD bdd.A : Lzk;
   L49
    LINENUMBER 556 L49
    ALOAD 0
    ALOAD 0
    GETFIELD bdd.x : Labp;
    PUTFIELD bdd.C : Labp;
   L50
    LINENUMBER 557 L50
    ALOAD 0
    INVOKESTATIC azd.J ()J
    PUTFIELD bdd.B : J
    GOTO L51
   L44
    LINENUMBER 561 L44
   FRAME FULL [bdd I I I zk I I I I T T I] []
    ALOAD 0
    ACONST_NULL
    PUTFIELD bdd.C : Labp;
    GOTO L51
   L40
    LINENUMBER 564 L40
   FRAME FULL [bdd I I I zk I I I I T T I] []
    ALOAD 0
    GETFIELD bdd.x : Labp;
    IFNULL L51
   L52
    LINENUMBER 566 L52
    ALOAD 0
    ILOAD 1
    ILOAD 5
    ISUB
    PUTFIELD bdd.y : I
   L53
    LINENUMBER 567 L53
    ALOAD 0
    ILOAD 2
    ILOAD 6
    ISUB
    PUTFIELD bdd.z : I
   L54
    LINENUMBER 568 L54
    ALOAD 0
    ALOAD 0
    GETFIELD bdd.v : Lzk;
    PUTFIELD bdd.A : Lzk;
   L55
    LINENUMBER 569 L55
    ALOAD 0
    ALOAD 0
    GETFIELD bdd.x : Labp;
    PUTFIELD bdd.C : Labp;
   L56
    LINENUMBER 570 L56
    ALOAD 0
    INVOKESTATIC azd.J ()J
    PUTFIELD bdd.B : J
   L51
    LINENUMBER 573 L51
   FRAME FULL [bdd I I I zk I I I I T T I] []
    ALOAD 0
    ACONST_NULL
    PUTFIELD bdd.x : Labp;
   L57
    LINENUMBER 574 L57
    ALOAD 0
    ACONST_NULL
    PUTFIELD bdd.v : Lzk;
    GOTO L25
   L34
    LINENUMBER 577 L34
   FRAME FULL [bdd I I I zk I I I I] []
    ALOAD 0
    GETFIELD bdd.t : Z
    IFEQ L58
    ALOAD 0
    GETFIELD bdd.s : Ljava/util/Set;
    INVOKEINTERFACE java/util/Set.isEmpty ()Z
    IFNE L58
   L59
    LINENUMBER 579 L59
    ALOAD 0
    ACONST_NULL
    CHECKCAST zk
    SIPUSH -999
    ICONST_0
    ALOAD 0
    GETFIELD bdd.F : I
    INVOKESTATIC ye.d (II)I
    ICONST_5
    INVOKEVIRTUAL bdd.managerHandleMouseClick (Lzk;III)V
   L60
    LINENUMBER 580 L60
    ALOAD 0
    GETFIELD bdd.s : Ljava/util/Set;
    INVOKEINTERFACE java/util/Set.iterator ()Ljava/util/Iterator;
    ASTORE 9
   L61
    LINENUMBER 582 L61
   FRAME FULL [bdd I I I zk I I I I java/util/Iterator] []
    ALOAD 9
    INVOKEINTERFACE java/util/Iterator.hasNext ()Z
    IFEQ L62
   L63
    LINENUMBER 584 L63
    ALOAD 9
    INVOKEINTERFACE java/util/Iterator.next ()Ljava/lang/Object;
    CHECKCAST zk
    ASTORE 10
   L64
    LINENUMBER 585 L64
    ALOAD 0
    ALOAD 10
    ALOAD 10
    GETFIELD zk.g : I
    ICONST_1
    ALOAD 0
    GETFIELD bdd.F : I
    INVOKESTATIC ye.d (II)I
    ICONST_5
    INVOKEVIRTUAL bdd.managerHandleMouseClick (Lzk;III)V
    GOTO L61
   L62
    LINENUMBER 588 L62
   FRAME FULL [bdd I I I zk I I I I java/util/Iterator] []
    ALOAD 0
    ACONST_NULL
    CHECKCAST zk
    SIPUSH -999
    ICONST_2
    ALOAD 0
    GETFIELD bdd.F : I
    INVOKESTATIC ye.d (II)I
    ICONST_5
    INVOKEVIRTUAL bdd.managerHandleMouseClick (Lzk;III)V
    GOTO L25
   L58
    LINENUMBER 590 L58
   FRAME FULL [bdd I I I zk I I I I] []
    ALOAD 0
    GETFIELD bdd.k : Lazd;
    GETFIELD azd.h : Lbje;
    GETFIELD bje.bn : Lxj;
    INVOKEVIRTUAL xj.o ()Labp;
    IFNULL L65
    ILOAD 3
    ALOAD 0
    GETFIELD bdd.k : Lazd;
    GETFIELD azd.u : Lazw;
    GETFIELD azw.U : Laza;
    INVOKEVIRTUAL aza.i ()I
    BIPUSH 100
    IADD
    IF_ICMPNE L66
   L67
    LINENUMBER 594 L67
    ALOAD 0
    ALOAD 4
    ILOAD 8
    ILOAD 3
    ICONST_3
    INVOKEVIRTUAL bdd.managerHandleMouseClick (Lzk;III)V
    GOTO L25
   L66
    LINENUMBER 598 L66
   FRAME FULL [bdd I I I zk I I I I] []
    ILOAD 8
    SIPUSH -999
    IF_ICMPEQ L68
    BIPUSH 42
    INVOKESTATIC org/lwjgl/input/Keyboard.isKeyDown (I)Z
    IFNE L69
    BIPUSH 54
    INVOKESTATIC org/lwjgl/input/Keyboard.isKeyDown (I)Z
    IFEQ L68
   L69
   FRAME FULL [bdd I I I zk I I I I] []
    ICONST_1
    GOTO L70
   L68
   FRAME FULL [bdd I I I zk I I I I] []
    ICONST_0
   L70
   FRAME FULL [bdd I I I zk I I I I] [I]
    ISTORE 11
   L71
    LINENUMBER 600 L71
    ILOAD 11
    IFEQ L72
   L73
    LINENUMBER 602 L73
    ALOAD 0
    ALOAD 4
    IFNULL L74
    ALOAD 4
    INVOKEVIRTUAL zk.e ()Z
    IFEQ L74
    ALOAD 4
    INVOKEVIRTUAL zk.d ()Labp;
    GOTO L75
   L74
   FRAME FULL [bdd I I I zk I I I I T T I] [bdd]
    ACONST_NULL
   L75
   FRAME FULL [bdd I I I zk I I I I T T I] [bdd abp]
    PUTFIELD bdd.N : Labp;
   L72
    LINENUMBER 605 L72
   FRAME FULL [bdd I I I zk I I I I T T I] []
    ALOAD 0
    ALOAD 4
    ILOAD 8
    ILOAD 3
    ILOAD 11
    IFEQ L76
    ICONST_1
    GOTO L77
   L76
   FRAME FULL [bdd I I I zk I I I I T T I] [bdd zk I I]
    ICONST_0
   L77
   FRAME FULL [bdd I I I zk I I I I T T I] [bdd zk I I I]
    INVOKEVIRTUAL bdd.managerHandleMouseClick (Lzk;III)V
    GOTO L25
   L65
   FRAME FULL [bdd I I I zk I I I I] []
    ILOAD 3
    IFLT L25
    ALOAD 0
    GETFIELD bdd.manager : Lcodechicken/nei/guihook/GuiContainerManager;
    ILOAD 1
    ILOAD 2
    ILOAD 3
    INVOKEVIRTUAL codechicken/nei/guihook/GuiContainerManager.mouseUp (III)V
   L25
    LINENUMBER 610 L25
   FRAME FULL [bdd I I I zk I I I I] []
    ALOAD 0
    GETFIELD bdd.k : Lazd;
    GETFIELD azd.h : Lbje;
    GETFIELD bje.bn : Lxj;
    INVOKEVIRTUAL xj.o ()Labp;
    IFNONNULL L78
   L79
    LINENUMBER 612 L79
    ALOAD 0
    LCONST_0
    PUTFIELD bdd.J : J
   L78
    LINENUMBER 615 L78
   FRAME FULL [bdd I I I zk I I I I] []
    ALOAD 0
    ICONST_0
    PUTFIELD bdd.t : Z
   L80
    LINENUMBER 616 L80
    RETURN
   L81
    LOCALVARIABLE slot1 Lzk; L22 L16 10
    LOCALVARIABLE iterator Ljava/util/Iterator; L20 L16 9
    LOCALVARIABLE flag1 Z L39 L34 11
    LOCALVARIABLE slot1 Lzk; L64 L62 10
    LOCALVARIABLE iterator Ljava/util/Iterator; L61 L58 9
    LOCALVARIABLE flag1 Z L71 L25 11
    LOCALVARIABLE this Lbdd; L0 L81 0
    LOCALVARIABLE p_146286_1_ I L0 L81 1
    LOCALVARIABLE p_146286_2_ I L0 L81 2
    LOCALVARIABLE p_146286_3_ I L0 L81 3
    LOCALVARIABLE slot Lzk; L2 L81 4
    LOCALVARIABLE l I L3 L81 5
    LOCALVARIABLE i1 I L4 L81 6
    LOCALVARIABLE flag Z L8 L81 7
    LOCALVARIABLE j1 I L9 L81 8
    MAXSTACK = 5
    MAXLOCALS = 12

  // access flags 0x2
  private a(Lzk;II)Z
   L0
    LINENUMBER 620 L0
    ALOAD 0
    ALOAD 1
    GETFIELD zk.h : I
    ALOAD 1
    GETFIELD zk.i : I
    BIPUSH 16
    BIPUSH 16
    ILOAD 2
    ILOAD 3
    INVOKEVIRTUAL bdd.c (IIIIII)Z
    IRETURN
   L1
    LOCALVARIABLE this Lbdd; L0 L1 0
    LOCALVARIABLE p_146981_1_ Lzk; L0 L1 1
    LOCALVARIABLE p_146981_2_ I L0 L1 2
    LOCALVARIABLE p_146981_3_ I L0 L1 3
    MAXSTACK = 7
    MAXLOCALS = 4

  // access flags 0x4
  protected c(IIIIII)Z
   L0
    LINENUMBER 625 L0
    ALOAD 0
    GETFIELD bdd.i : I
    ISTORE 7
   L1
    LINENUMBER 626 L1
    ALOAD 0
    GETFIELD bdd.r : I
    ISTORE 8
   L2
    LINENUMBER 627 L2
    ILOAD 5
    ILOAD 7
    ISUB
    ISTORE 5
   L3
    LINENUMBER 628 L3
    ILOAD 6
    ILOAD 8
    ISUB
    ISTORE 6
   L4
    LINENUMBER 629 L4
    ILOAD 5
    ILOAD 1
    ICONST_1
    ISUB
    IF_ICMPLT L5
    ILOAD 5
    ILOAD 1
    ILOAD 3
    IADD
    ICONST_1
    IADD
    IF_ICMPGE L5
    ILOAD 6
    ILOAD 2
    ICONST_1
    ISUB
    IF_ICMPLT L5
    ILOAD 6
    ILOAD 2
    ILOAD 4
    IADD
    ICONST_1
    IADD
    IF_ICMPGE L5
    ICONST_1
    GOTO L6
   L5
   FRAME FULL [bdd I I I I I I I I] []
    ICONST_0
   L6
   FRAME FULL [bdd I I I I I I I I] [I]
    IRETURN
   L7
    LOCALVARIABLE this Lbdd; L0 L7 0
    LOCALVARIABLE p_146978_1_ I L0 L7 1
    LOCALVARIABLE p_146978_2_ I L0 L7 2
    LOCALVARIABLE p_146978_3_ I L0 L7 3
    LOCALVARIABLE p_146978_4_ I L0 L7 4
    LOCALVARIABLE p_146978_5_ I L0 L7 5
    LOCALVARIABLE p_146978_6_ I L0 L7 6
    LOCALVARIABLE k1 I L1 L7 7
    LOCALVARIABLE l1 I L2 L7 8
    MAXSTACK = 3
    MAXLOCALS = 9

  // access flags 0x4
  protected a(Lzk;III)V
   L0
    LINENUMBER 634 L0
    ALOAD 1
    IFNULL L1
   L2
    LINENUMBER 636 L2
    ALOAD 1
    GETFIELD zk.g : I
    ISTORE 2
   L1
   FRAME FULL [bdd zk I I I] []
    ALOAD 0
    GETFIELD bdd.manager : Lcodechicken/nei/guihook/GuiContainerManager;
    ILOAD 2
    ILOAD 3
    ILOAD 4
    INVOKEVIRTUAL codechicken/nei/guihook/GuiContainerManager.handleSlotClick (III)V
   L3
    LINENUMBER 640 L3
    RETURN
   L4
    LOCALVARIABLE this Lbdd; L0 L4 0
    LOCALVARIABLE p_146984_1_ Lzk; L0 L4 1
    LOCALVARIABLE p_146984_2_ I L0 L4 2
    LOCALVARIABLE p_146984_3_ I L0 L4 3
    LOCALVARIABLE p_146984_4_ I L0 L4 4
    MAXSTACK = 4
    MAXLOCALS = 5

  // access flags 0x4
  protected a(CI)V
    ALOAD 0
    GETFIELD bdd.manager : Lcodechicken/nei/guihook/GuiContainerManager;
    ILOAD 2
    ILOAD 1
    INVOKEVIRTUAL codechicken/nei/guihook/GuiContainerManager.lastKeyTyped (IC)Z
    IFEQ L0
    RETURN
   L0
    LINENUMBER 644 L0
   FRAME FULL [bdd I I] []
    ILOAD 2
    ICONST_1
    IF_ICMPEQ L1
    ILOAD 2
    ALOAD 0
    GETFIELD bdd.k : Lazd;
    GETFIELD azd.u : Lazw;
    GETFIELD azw.Q : Laza;
    INVOKEVIRTUAL aza.i ()I
    IF_ICMPNE L2
   L1
    LINENUMBER 646 L1
   FRAME FULL [bdd I I] []
    ALOAD 0
    GETFIELD bdd.k : Lazd;
    GETFIELD azd.h : Lbje;
    INVOKEVIRTUAL bje.k ()V
   L2
    LINENUMBER 649 L2
   FRAME FULL [bdd I I] []
    ALOAD 0
    ILOAD 2
    INVOKEVIRTUAL bdd.a (I)Z
    POP
   L3
    LINENUMBER 651 L3
    ALOAD 0
    GETFIELD bdd.u : Lzk;
    IFNULL L4
    ALOAD 0
    GETFIELD bdd.u : Lzk;
    INVOKEVIRTUAL zk.e ()Z
    IFEQ L4
   L5
    LINENUMBER 653 L5
    ILOAD 2
    ALOAD 0
    GETFIELD bdd.k : Lazd;
    GETFIELD azd.u : Lazw;
    GETFIELD azw.U : Laza;
    INVOKEVIRTUAL aza.i ()I
    IF_ICMPNE L6
   L7
    LINENUMBER 655 L7
    ALOAD 0
    ALOAD 0
    GETFIELD bdd.u : Lzk;
    ALOAD 0
    GETFIELD bdd.u : Lzk;
    GETFIELD zk.g : I
    ICONST_0
    ICONST_3
    INVOKEVIRTUAL bdd.managerHandleMouseClick (Lzk;III)V
    GOTO L4
   L6
    LINENUMBER 657 L6
   FRAME FULL [bdd I I] []
    ILOAD 2
    ALOAD 0
    GETFIELD bdd.k : Lazd;
    GETFIELD azd.u : Lazw;
    GETFIELD azw.S : Laza;
    INVOKEVIRTUAL aza.i ()I
    IF_ICMPNE L4
   L8
    LINENUMBER 659 L8
    ALOAD 0
    ALOAD 0
    GETFIELD bdd.u : Lzk;
    ALOAD 0
    GETFIELD bdd.u : Lzk;
    GETFIELD zk.g : I
    INVOKESTATIC bdd.m ()Z
    IFEQ L9
    ICONST_1
    GOTO L10
   L9
   FRAME FULL [bdd I I] [bdd zk I]
    ICONST_0
   L10
   FRAME FULL [bdd I I] [bdd zk I I]
    ICONST_4
    INVOKEVIRTUAL bdd.managerHandleMouseClick (Lzk;III)V
   L4
    LINENUMBER 662 L4
   FRAME FULL [bdd I I] []
    RETURN
   L11
    LOCALVARIABLE this Lbdd; L0 L11 0
    LOCALVARIABLE par1 C L0 L11 1
    LOCALVARIABLE par2 I L0 L11 2
    MAXSTACK = 5
    MAXLOCALS = 3

  // access flags 0x4
  protected a(I)Z
   L0
    LINENUMBER 666 L0
    ALOAD 0
    GETFIELD bdd.k : Lazd;
    GETFIELD azd.h : Lbje;
    GETFIELD bje.bn : Lxj;
    INVOKEVIRTUAL xj.o ()Labp;
    IFNONNULL L1
    ALOAD 0
    GETFIELD bdd.u : Lzk;
    IFNULL L1
   L2
    LINENUMBER 668 L2
    ICONST_0
    ISTORE 2
   L3
   FRAME FULL [bdd I I] []
    ILOAD 2
    BIPUSH 9
    IF_ICMPGE L1
   L4
    LINENUMBER 670 L4
    ILOAD 1
    ALOAD 0
    GETFIELD bdd.k : Lazd;
    GETFIELD azd.u : Lazw;
    GETFIELD azw.ac : [Laza;
    ILOAD 2
    AALOAD
    INVOKEVIRTUAL aza.i ()I
    IF_ICMPNE L5
   L6
    LINENUMBER 672 L6
    ALOAD 0
    ALOAD 0
    GETFIELD bdd.u : Lzk;
    ALOAD 0
    GETFIELD bdd.u : Lzk;
    GETFIELD zk.g : I
    ILOAD 2
    ICONST_2
    INVOKEVIRTUAL bdd.managerHandleMouseClick (Lzk;III)V
   L7
    LINENUMBER 673 L7
    ICONST_1
    IRETURN
   L5
    LINENUMBER 668 L5
   FRAME FULL [bdd I I] []
    IINC 2 1
    GOTO L3
   L1
    LINENUMBER 678 L1
   FRAME FULL [bdd I] []
    ICONST_0
    IRETURN
   L8
    LOCALVARIABLE j I L3 L1 2
    LOCALVARIABLE this Lbdd; L0 L8 0
    LOCALVARIABLE p_146983_1_ I L0 L8 1
    MAXSTACK = 5
    MAXLOCALS = 3

  // access flags 0x1
  public b()V
   L0
    LINENUMBER 683 L0
    ALOAD 0
    GETFIELD bdd.k : Lazd;
    GETFIELD azd.h : Lbje;
    IFNULL L1
   L2
    LINENUMBER 685 L2
    ALOAD 0
    GETFIELD bdd.h : Lye;
    ALOAD 0
    GETFIELD bdd.k : Lazd;
    GETFIELD azd.h : Lbje;
    INVOKEVIRTUAL ye.b (Lxl;)V
   L1
    LINENUMBER 687 L1
   FRAME FULL [bdd] []
    RETURN
   L3
    LOCALVARIABLE this Lbdd; L0 L3 0
    MAXSTACK = 2
    MAXLOCALS = 1

  // access flags 0x1
  public f()Z
   L0
    LINENUMBER 691 L0
    ICONST_0
    IRETURN
   L1
    LOCALVARIABLE this Lbdd; L0 L1 0
    MAXSTACK = 1
    MAXLOCALS = 1

  // access flags 0x1
  public c()V
   L0
    LINENUMBER 696 L0
    ALOAD 0
    INVOKESPECIAL bcd.c ()V
    ALOAD 0
    GETFIELD bdd.manager : Lcodechicken/nei/guihook/GuiContainerManager;
    INVOKEVIRTUAL codechicken/nei/guihook/GuiContainerManager.updateScreen ()V
   L1
    LINENUMBER 698 L1
    ALOAD 0
    GETFIELD bdd.k : Lazd;
    GETFIELD azd.h : Lbje;
    INVOKEVIRTUAL bje.Z ()Z
    IFEQ L2
    ALOAD 0
    GETFIELD bdd.k : Lazd;
    GETFIELD azd.h : Lbje;
    GETFIELD bje.L : Z
    IFEQ L3
   L2
    LINENUMBER 700 L2
   FRAME FULL [bdd] []
    ALOAD 0
    GETFIELD bdd.k : Lazd;
    GETFIELD azd.h : Lbje;
    INVOKEVIRTUAL bje.k ()V
   L3
    LINENUMBER 702 L3
   FRAME FULL [bdd] []
    RETURN
   L4
    LOCALVARIABLE this Lbdd; L0 L4 0
    MAXSTACK = 1
    MAXLOCALS = 1

  // access flags 0x8
  static <clinit>()V
   L0
    LINENUMBER 29 L0
    NEW bqo
    DUP
    LDC "textures/gui/container/inventory.png"
    INVOKESPECIAL bqo.<init> (Ljava/lang/String;)V
    PUTSTATIC bdd.a : Lbqo;
    RETURN
    MAXSTACK = 3
    MAXLOCALS = 0

  // access flags 0x1
  public a(Lazd;II)V
    ALOAD 0
    ALOAD 1
    ILOAD 2
    ILOAD 3
    INVOKESPECIAL bcd.a (Lazd;II)V
    ALOAD 1
    GETFIELD azd.n : Lbcd;
    ALOAD 0
    IF_ACMPNE L0
    ALOAD 0
    NEW codechicken/nei/guihook/GuiContainerManager
    DUP
    ALOAD 0
    INVOKESPECIAL codechicken/nei/guihook/GuiContainerManager.<init> (Lnet/minecraft/client/gui/inventory/GuiContainer;)V
    PUTFIELD bdd.manager : Lcodechicken/nei/guihook/GuiContainerManager;
    ALOAD 0
    GETFIELD bdd.manager : Lcodechicken/nei/guihook/GuiContainerManager;
    INVOKEVIRTUAL codechicken/nei/guihook/GuiContainerManager.load ()V
   L0
   FRAME FULL [bdd azd I I] []
    RETURN
    MAXSTACK = 4
    MAXLOCALS = 4

  // access flags 0x1
  public l()V
    ALOAD 0
    GETFIELD bdd.manager : Lcodechicken/nei/guihook/GuiContainerManager;
    INVOKEVIRTUAL codechicken/nei/guihook/GuiContainerManager.handleKeyboardInput ()V
    RETURN
    MAXSTACK = 1
    MAXLOCALS = 1

  // access flags 0x1
  public d()V
    ALOAD 0
    INVOKESPECIAL bcd.d ()V
    ALOAD 0
    GETFIELD bdd.manager : Lcodechicken/nei/guihook/GuiContainerManager;
    INVOKEVIRTUAL codechicken/nei/guihook/GuiContainerManager.handleMouseWheel ()V
    RETURN
    MAXSTACK = 1
    MAXLOCALS = 1

  // access flags 0x1
  public public_func_73869_a(CI)V
    ALOAD 0
    ILOAD 1
    ILOAD 2
    INVOKEVIRTUAL bdd.a (CI)V
    RETURN
    MAXSTACK = 3
    MAXLOCALS = 3

  // access flags 0x1
  public public_func_146984_a(Lzk;III)V
    ALOAD 0
    ALOAD 1
    ILOAD 2
    ILOAD 3
    ILOAD 4
    INVOKEVIRTUAL bdd.a (Lzk;III)V
    RETURN
    MAXSTACK = 5
    MAXLOCALS = 5

  // access flags 0x1
  public managerHandleMouseClick(Lzk;III)V
    ALOAD 0
    GETFIELD bdd.manager : Lcodechicken/nei/guihook/GuiContainerManager;
    ALOAD 1
    ILOAD 2
    ILOAD 3
    ILOAD 4
    INVOKEVIRTUAL codechicken/nei/guihook/GuiContainerManager.handleMouseClick (Lnet/minecraft/inventory/Slot;III)V
    RETURN
    MAXSTACK = 5
    MAXLOCALS = 5
}
